newproj/__init__.py
newproj/cli.py
newproj/generator.py
newproj/templates/__init__.py
newproj/templates/basic.py
newproj/templates/pygame_template.py
newproj_bobv1-1.0.0.dist-info/licenses/Licence.md
newproj_bobv1-1.0.0.dist-info/METADATA
newproj_bobv1-1.0.0.dist-info/WHEEL
newproj_bobv1-1.0.0.dist-info/entry_points.txt
newproj_bobv1-1.0.0.dist-info/top_level.txt
newproj_bobv1-1.0.0.dist-info/RECORD
