Metadata-Version: 2.4
Name: newproj-bobv1
Version: 1.0.0
Summary: A fast, interactive Python project generator
Home-page: https://github.com/Golden021/newproj
Author: Liam G
Author-email: TemNet021@outlook.com
Project-URL: Bug Reports, https://github.com/Golden021/newproj/issues
Project-URL: Source, https://github.com/Golden021/newproj
Project-URL: Documentation, https://github.com/Golden021/newproj#readme
Keywords: python project generator boilerplate template cli interactive pygame
Classifier: Development Status :: 5 - Production/Stable
Classifier: Intended Audience :: Developers
Classifier: Topic :: Software Development :: Code Generators
Classifier: Topic :: Software Development :: Libraries :: Python Modules
Classifier: License :: OSI Approved :: MIT License
Classifier: Operating System :: OS Independent
Classifier: Programming Language :: Python :: 3
Classifier: Programming Language :: Python :: 3.7
Classifier: Programming Language :: Python :: 3.8
Classifier: Programming Language :: Python :: 3.9
Classifier: Programming Language :: Python :: 3.10
Classifier: Programming Language :: Python :: 3.11
Classifier: Programming Language :: Python :: 3.12
Classifier: Programming Language :: Python :: 3.13
Requires-Python: >=3.7
License-File: Licence.md
Dynamic: author
Dynamic: author-email
Dynamic: classifier
Dynamic: description
Dynamic: description-content-type
Dynamic: home-page
Dynamic: keywords
Dynamic: license-file
Dynamic: project-url
Dynamic: requires-python
Dynamic: summary
